Workbook

Sheet Final Project Dataset
A1: Transaction_ID | B1: Date | C1: Customer_ID | D1: Customer_Name | E1: Product_ID | F1: Product_Name | G1: Category | H1: Quantity | I1: Unit_Price | J1: Payment_Method | K1: Region | L1: Customer_Segment | M1: Customer_Since | N1: Total_Amount | O1: Timestamp
A2: TRX0155 | B2: 45393 | C2: CUST023 | D2: Paul Baker | E2: P009 | F2: Monitor | G2: Electronics | H2: 3 | I2: 249.99 | J2: Cash | K2: Central | L2: Basic | M2: 44425 | N2: 749.97 | O2: =IF(A2<>"",IF(O2="",NOW(),O2),"") -> 0
A3: TRX0023 | B3: 45396 | C3: CUST013 | D3: Joseph Jackson | E3: P009 | F3: Monitor | G3: Electronics | H3: 3 | I3: 249.99 | J3: Credit Card | K3: Central | L3: Premium | M3: 44575 | N3: 749.97 | O3: =IF(A3<>"",IF(O3="",NOW(),O3),"") -> 0
A4: TRX0139 | B4: 45399 | C4: CUST021 | D4: Kevin Scott | E4: P005 | F4: Blender | G4: Appliances | H4: 3 | I4: 59.99 | J4: PayPal | K4: South | L4: Standard | M4: 45262 | N4: 179.97 | O4: =IF(A4<>"",IF(O4="",NOW(),O4),"") -> 0
A5: TRX0043 | B5: 45400 | C5: CUST046 | D5: Kathleen Bennett | E5: P005 | F5: Blender | G5: Appliances | H5: 3 | I5: 59.99 | J5: Cash | K5: North | L5: Premium | M5: 45114 | N5: 179.97 | O5: =IF(A5<>"",IF(O5="",NOW(),O5),"") -> 0
A6: TRX0212 | B6: 45400 | C6: CUST003 | D6: Michael Brown | E6: P008 | F6: Bookshelf | G6: Furniture | H6: 5 | I6: 149.99 | J6: Credit Card | K6: North | L6: Premium | M6: 45295 | N6: 749.95 | O6: =IF(A6<>"",IF(O6="",NOW(),O6),"") -> 0
A7: TRX0092 | B7: 45403 | C7: CUST024 | D7: Dorothy Nelson | E7: P005 | F7: Blender | G7: Appliances | H7: 2 | I7: 59.99 | J7: Cash | K7: West | L7: Standard | M7: 44746 | N7: 119.98 | O7: =IF(A7<>"",IF(O7="",NOW(),O7),"") -> 0
A8: TRX0193 | B8: 45403 | C8: CUST024 | D8: Dorothy Nelson | E8: P003 | F8: Headphones | G8: Electronics | H8: 5 | I8: 149.99 | J8: Credit Card | K8: Central | L8: Standard | M8: 44418 | N8: 749.95 | O8: =IF(A8<>"",IF(O8="",NOW(),O8),"") -> 0
A9: TRX0240 | B9: 45403 | C9: CUST017 | D9: Charles Allen | E9: P005 | F9: Blender | G9: Appliances | H9: 3 | I9: 59.99 | J9: Debit Card | K9: South | L9: Basic | M9: 45007 | N9: 179.97 | O9: =IF(A9<>"",IF(O9="",NOW(),O9),"") -> 0
A10: TRX0135 | B10: 45405 | C10: CUST009 | D10: Robert Thomas | E10: P001 | F10: Laptop | G10: Electronics | H10: 3 | I10: 899.99 | J10: PayPal | K10: East | L10: Standard | M10: 45299 | N10: 2699.97 | O10: =IF(A10<>"",IF(O10="",NOW(),O10),"") -> 0
A11: TRX0185 | B11: 45408 | C11: CUST026 | D11: Karen Hill | E11: P005 | F11: Blender | G11: Appliances | H11: 3 | I11: 59.99 | J11: Cash | K11: West | L11: Premium | M11: 45207 | N11: 179.97 | O11: =IF(A11<>"",IF(O11="",NOW(),O11),"") -> 0
A12: TRX0138 | B12: 45408 | C12: CUST022 | D12: Susan Green | E12: P008 | F12: Bookshelf | G12: Furniture | H12: 1 | I12: 149.99 | J12: Credit Card | K12: West | L12: Standard | M12: 45103 | N12: 149.99 | O12: =IF(A12<>"",IF(O12="",NOW(),O12),"") -> 0
A13: TRX0209 | B13: 45408 | C13: CUST046 | D13: Kathleen Bennett | E13: P008 | F13: Bookshelf | G13: Furniture | H13: 5 | I13: 149.99 | J13: Debit Card | K13: North | L13: Basic | M13: 44830 | N13: 749.95 | O13: =IF(A13<>"",IF(O13="",NOW(),O13),"") -> 0
... A251: TRX0064 | B251: 45758 | C251: CUST031 | D251: Steven Turner | E251: P010 | F251: Keyboard | G251: Electronics | H251: 3 | I251: 89.99 | J251: Debit Card | K251: North | L251: Premium | M251: 44878 | N251: 269.97 | O251: =IF(A251<>"",IF(O251="",NOW(),O251),"") -> 0

Sheet Scenario Summary 2
B2: Scenario Summary
D3: Current Values: | E3: pessimistic | F3: normal | G3: optimistic
E4: Created by NIYATI PATEL on 13-10-2026 Modified by NIYATI PATEL on 13-10-2026 | F4: Created by NIYATI PATEL on 13-10-2026 Modified by NIYATI PATEL on 13-10-2026 | G4: Created by NIYATI PATEL on 13-10-2026
B5: Changing Cells:
C6: $B$24 | D6: 229192.47 | E6: 200000 | F6: 229192.47 | G6: 275000
B7: Result Cells:
C8: $B$24 | D8: 229192.47 | E8: 200000 | F8: 229192.47 | G8: 275000
B9: Notes: Current Values column represents values of changing cells at
B10: time Scenario Summary Report was created. Changing cells for each
B11: scenario are highlighted in gray.

Sheet Analysis
A1: Customer Transaction Analysis
A2: Total Revenue | B2: =SUM('Final Project Dataset'!N:N) -> 229192.47
A3: Total Transactions | B3: =COUNTA('Final Project Dataset'!A:A)-1 -> 250
A4: Total Quantity Sold | B4: =SUM('Final Project Dataset'!H:H) -> 753
A5: Average Transaction Value | B5: =AVERAGE('Final Project Dataset'!N:N) -> 916.76988
A8: Date and time Analysis
A9: today's date | B9: =TODAY() -> 46308
A10: current date and time | B10: =NOW() -> 46308.799
A11: first transaction date | B11: =MIN('Final Project Dataset'!B2:B251) -> 45393
A12: last transaction date | B12: =MAX('Final Project Dataset'!B2:B251) -> 45758
A13: customer duration | B13: =DATEDIF(B11,B12,"d") -> 365
A15: End of last transcation month | B15: =EOMONTH(B12,0) -> 45777
A17: Filter analysis
A18: Select region
A19: North
A20: Filtered Transactions
A21: {=_xlfn._xlws.FILTER('Final Project Dataset'!A2:N251,'Final Project Dataset'!K2:K251=B18,"no matching transaction")} -> no matching transaction
A23: what if analysis
A24: current total revenue | B24: 229192.47
A25: target revenue | B25: 250000
A26: additional revenue needed | B26: =B25-B24 -> 20807.53
A27: average revenue per unit | B27: =B24/SUM('Final Project Dataset'!H2:H251) -> 304.37247
A28: requried total quantity | B28: =B25/B27 -> 821.36206
A29: test Quantity | B29: 821.36206
A30: test revenue | B30: =B29*B27 -> 250000

Sheet regression analysis
A1: SUMMARY OUTPUT
A3: Regression Statistics
A4: Multiple R | B4: 0.45808036
A5: R Square | B5: 0.20983762
A6: Adjusted R Square | B6: 0.20665148
A7: Standard Error | B7: 919.60715
A8: Observations | B8: 250
A10: ANOVA
B11: df | C11: SS | D11: MS | E11: F | F11: Significance F
A12: Regression | B12: 1 | C12: 55695917 | D12: 55695917 | E12: 65.859537 | F12: 2.2586479e-14
A13: Residual | B13: 248 | C13: 2.0972797e+08 | D13: 845677.32
A14: Total | B14: 249 | C14: 2.6542389e+08
B16: Coefficients | C16: Standard Error | D16: t Stat | E16: P-value | F16: Lower 95% | G16: Upper 95% | H16: Lower 95.0% | I16: Upper 95.0%
A17: Intercept | B17: -148.85465 | C17: 143.61334 | D17: -1.0364959 | E17: 0.3009804 | F17: -431.712 | G17: 134.0027 | H17: -431.712 | I17: 134.0027
A18: quantity | B18: 353.793 | C18: 43.595323 | D18: 8.1153889 | E18: 2.2586479e-14 | F18: 267.92872 | G18: 439.65729 | H18: 267.92872 | I18: 439.65729

Sheet product analysis
A1: product name | B1: purchase frequnecy | D1: most frequency pirchased product | E1: purchase count
A2: {=_xlfn.UNIQUE('Final Project Dataset'!F2:F251)} -> Monitor | B2: {=COUNTIF('Final Project Dataset'!F$2:F$251,_xlfn.ANCHORARRAY(A2))} -> 26 | D2: =INDEX(_xlfn.ANCHORARRAY(A2),MATCH(MAX(_xlfn.ANCHORARRAY(B2)),_xlfn.ANCHORARRAY(B2),0)) -> Bookshelf | E2: =MAX(_xlfn.ANCHORARRAY(B2)) -> 35
A3: Blender | B3: 29
A4: Bookshelf | B4: 35
A5: Headphones | B5: 16
A6: Laptop | B6: 24
A7: Smartphone | B7: 31
A8: Desk | B8: 26
A9: Coffee Maker | B9: 14
A10: Keyboard | B10: 34
A11: Office Chair | B11: 15

Sheet regression
A1: quantity | B1: total amount
A2: ='Final Project Dataset'!H2 -> 3 | B2: ='Final Project Dataset'!N2 -> 749.97
A3: ='Final Project Dataset'!H3 -> 3 | B3: ='Final Project Dataset'!N3 -> 749.97
A4: ='Final Project Dataset'!H4 -> 3 | B4: ='Final Project Dataset'!N4 -> 179.97
A5: ='Final Project Dataset'!H5 -> 3 | B5: ='Final Project Dataset'!N5 -> 179.97
A6: ='Final Project Dataset'!H6 -> 5 | B6: ='Final Project Dataset'!N6 -> 749.95
A7: ='Final Project Dataset'!H7 -> 2 | B7: ='Final Project Dataset'!N7 -> 119.98
A8: ='Final Project Dataset'!H8 -> 5 | B8: ='Final Project Dataset'!N8 -> 749.95
A9: ='Final Project Dataset'!H9 -> 3 | B9: ='Final Project Dataset'!N9 -> 179.97
A10: ='Final Project Dataset'!H10 -> 3 | B10: ='Final Project Dataset'!N10 -> 2699.97
A11: ='Final Project Dataset'!H11 -> 3 | B11: ='Final Project Dataset'!N11 -> 179.97
A12: ='Final Project Dataset'!H12 -> 1 | B12: ='Final Project Dataset'!N12 -> 149.99
A13: ='Final Project Dataset'!H13 -> 5 | B13: ='Final Project Dataset'!N13 -> 749.95
... A251: ='Final Project Dataset'!H251 -> 3 | B251: ='Final Project Dataset'!N251 -> 269.97
